{
  "slug": "copyright-vs-trademark-difference-india-what-should-you-register-2025",
  "type": "post",
  "title": "Copyright vs Trademark Difference India: What Should You Register?Copyright vs. Trademark: The Ultimate 2025 Guide - BookMyTM",
  "h1": "Copyright vs. Trademark: The Ultimate 2025 Guide for Creators & Founders",
  "datePublished": "",
  "featuredImage": "https://bookmytm.com/wp-content/uploads/2025/12/blog_10_copyright_vs_tm_1920_1080.webp",
  "blocks": [
    {
      "type": "heading",
      "level": 1,
      "text": "Copyright vs. Trademark: The Ultimate 2025 Guide for Creators & Founders"
    },
    {
      "type": "paragraph",
      "text": "Logo, Book, or Code? Learn the difference between Copyright and Trademark in India to avoid costly legal mistakes."
    },
    {
      "type": "paragraph",
      "text": "Written By"
    },
    {
      "type": "paragraph",
      "text": "BookMyTM Team"
    },
    {
      "type": "paragraph",
      "text": "Reading Time"
    },
    {
      "type": "paragraph",
      "text": "7 Mins"
    },
    {
      "type": "paragraph",
      "text": "Imagine this: You write a best-selling book called \"The 2025 Startup Guide\". You design a cool Logo for the cover. You build a Website to sell it."
    },
    {
      "type": "paragraph",
      "text": "Now, a competitor comes along. They copy your book's text. They copy your logo. They copy your website code."
    },
    {
      "type": "paragraph",
      "text": "You run to a lawyer. The lawyer asks: \"Did you register a Trademark or a Copyright?\""
    },
    {
      "type": "paragraph",
      "text": "You stare blankly. \"Aren't they the same thing?\""
    },
    {
      "type": "paragraph",
      "text": "This is the single most expensive mistake creative professionals make."
    },
    {
      "type": "paragraph",
      "text": "Trademark and Copyright are two completely different legal weapons. Using the wrong one is like trying to cut a steak with a spoon—it just won't work."
    },
    {
      "type": "paragraph",
      "text": "In this comprehensive 1500-word guide, BookMyTM breaks down the complex world of IP. We will explain exactly what protects what, so you never leave your hard work exposed again."
    },
    {
      "type": "heading",
      "level": 4,
      "text": "The Golden Rule"
    },
    {
      "type": "paragraph",
      "text": "\"If it identifies WHO made it, it's a Trademark (e.g., Nike). If it protects WHAT was made, it's Copyright (e.g., Harry Potter books).\""
    },
    {
      "type": "heading",
      "level": 2,
      "text": "1. The Fundamental Difference"
    },
    {
      "type": "paragraph",
      "text": "The difference is simple if you remember this rule:"
    },
    {
      "type": "list",
      "ordered": false,
      "items": [
        "Trademark protects your IDENTITY (Who you are).",
        "Copyright protects your EXPRESSION (What you created)."
      ]
    },
    {
      "type": "heading",
      "level": 3,
      "text": "Trademark (The Brand Guard)"
    },
    {
      "type": "paragraph",
      "text": "It protects things that identify the source of a product. Examples: Brand Name (Nike), Logo (The Swoosh), Slogan (\"Just Do It\"), Sound Mark (Netflix \"Tu-Dum\"). Goal: To prevent consumer confusion."
    },
    {
      "type": "heading",
      "level": 3,
      "text": "Copyright (The Content Guard)"
    },
    {
      "type": "paragraph",
      "text": "It protects original literary, artistic, dramatic, and musical works. Examples: Books, Songs, Movies, Paintings, Software Code, Website Design. Goal: To prevent unauthorized copying or distribution."
    },
    {
      "type": "heading",
      "level": 2,
      "text": "2. The \"Logo\" Confusion: Do you need both?"
    },
    {
      "type": "paragraph",
      "text": "This is where 99% of founders get stuck."
    },
    {
      "type": "paragraph",
      "text": "Scenario: You design a beautiful artistic logo for your coffee shop."
    },
    {
      "type": "list",
      "ordered": false,
      "items": [
        "As a Brand Name: It is a Trademark. You put it on your cups so people know the coffee is from you.",
        "As an Artwork: It is a Copyright. An artist drew it. It is an artistic creation."
      ]
    },
    {
      "type": "paragraph",
      "text": "Q: So, which one should I file?"
    },
    {
      "type": "paragraph",
      "text": "A: For most businesses, Trademark is Priority #1. Why? because Trademark protects the commercial value of the logo. Copyright only protects the artistic value. If someone opens a shop with a similar logo, a Trademark Lawsuit is much stronger and faster than a Copyright Lawsuit."
    },
    {
      "type": "paragraph",
      "text": "Pro Tip: File Copyright for your logo ONLY if the artwork itself is extremely unique and valuable (like a painting), independent of the brand name."
    },
    {
      "type": "heading",
      "level": 2,
      "text": "3. What about Software & Apps?"
    },
    {
      "type": "paragraph",
      "text": "This is a grey area in Indian Law."
    },
    {
      "type": "list",
      "ordered": false,
      "items": [
        "The Code: Protected by Copyright. (Literary Work).",
        "The App Name & Icon: Protected by Trademark.",
        "The Functionality: Protected by Patent (Very hard to get for software in India)."
      ]
    },
    {
      "type": "paragraph",
      "text": "If you built a SaaS platform: 1. Trademark the name \"Zoho\" or \"Freshworks\". 2. Copyright the source code to stop ex-employees from stealing it."
    },
    {
      "type": "heading",
      "level": 2,
      "text": "4. Duration & Maintenance"
    },
    {
      "type": "paragraph",
      "text": "Trademark: Valid for 10 Years (Renewable indefinitely). Must be used commercially (\"Use it or lose it\"). Copyright: Valid for Lifetime of Author + 60 Years. One-time registration. No usage requirement."
    },
    {
      "type": "heading",
      "level": 2,
      "text": "5. Registration Process: A Quick Comparison"
    },
    {
      "type": "heading",
      "level": 3,
      "text": "Trademark Process"
    },
    {
      "type": "list",
      "ordered": true,
      "items": [
        "Search: Check availability.",
        "File: Form TM-A.",
        "Examination: Registrar checks for conflicts.",
        "Journal: Published for public opposition (4 months).",
        "Registration: Certificate issued."
      ]
    },
    {
      "type": "paragraph",
      "text": "Timeline: 6 to 12 months."
    },
    {
      "type": "heading",
      "level": 3,
      "text": "Copyright Process"
    },
    {
      "type": "list",
      "ordered": true,
      "items": [
        "File: Form XIV.",
        "Waiting Period: Mandatory 30-day wait for objections.",
        "Examination: Discrepancy letter is common.",
        "Registration: Certificate issued (ROC)."
      ]
    },
    {
      "type": "paragraph",
      "text": "Timeline: 2 to 6 months."
    },
    {
      "type": "heading",
      "level": 2,
      "text": "6. Real-World Case Studies"
    },
    {
      "type": "paragraph",
      "text": "Let’s look at how big brands use both."
    },
    {
      "type": "paragraph",
      "text": "Case Study: Harry Potter Trademark: The words \"Harry Potter\", \"Hogwarts\", and the lightning bolt logo are Trademarks. You cannot sell \"Harry Potter Shoes\". Copyright: The story inside the books and the script of the movies are Copyright. You cannot rewrite the book and sell it."
    },
    {
      "type": "paragraph",
      "text": "Case Study: Coca-Cola Trademark: The name \"Coca-Cola\" and the curvy bottle shape. Copyright: The specific advertising jingles and TV commercials they produce. Trade Secret: The actual recipe (Formula)."
    },
    {
      "type": "heading",
      "level": 2,
      "text": "7. When to choose what? (The Checklist)"
    },
    {
      "type": "paragraph",
      "text": "Choose TRADEMARK if: [ ] You are launching a Company Name. [ ] You are launching a Product Brand. [ ] You designed a Logo. [ ] You have a catchy Tagline."
    },
    {
      "type": "paragraph",
      "text": "Choose COPYRIGHT if: [ ] You wrote a Book or E-book. [ ] You recorded a Song or Video Course. [ ] You wrote Software Code. [ ] You took a Photograph. [ ] You designed a Website UI/UX."
    },
    {
      "type": "heading",
      "level": 2,
      "text": "Conclusion: Build Your Moat"
    },
    {
      "type": "paragraph",
      "text": "Intellectual Property is the moat around your business castle. Trademark protects the flag on top of the castle. Copyright protects the treasures inside the castle."
    },
    {
      "type": "paragraph",
      "text": "You wouldn't leave your house unlocked. Why leave your business exposed?"
    },
    {
      "type": "paragraph",
      "text": "Still Confused? Don't worry. IP Law is complex. That is why BookMyTM exists. Send us your creation (Name, Logo, Book, or Code), and our attorneys will tell you exactly which protection you need. We handle the paperwork, so you can focus on creating."
    },
    {
      "type": "image",
      "src": "https://bookmytm.com/wp-content/uploads/2025/12/blog_10_copyright_vs_tm_1920_1080.webp",
      "alt": "Copyright vs Trademark"
    },
    {
      "type": "paragraph",
      "text": "Total Reads"
    },
    {
      "type": "paragraph",
      "text": "3,892"
    },
    {
      "type": "paragraph",
      "text": "Have questions?"
    },
    {
      "type": "heading",
      "level": 3,
      "text": "Get Expert Advice"
    },
    {
      "type": "paragraph",
      "text": "Fill the details below for a callback."
    },
    {
      "type": "heading",
      "level": 2,
      "text": "Frequently Asked Questions"
    }
  ]
}